backend.py
data_handler.py
expectation_maximization.py
helpers.py
kernels_cupy.py
kernels_numba.py
kernels_numpy.py
logger.py
mmsbm.py
mmsbm-1.0.5.dist-info/licenses/LICENSE.txt
mmsbm-1.0.5.dist-info/METADATA
mmsbm-1.0.5.dist-info/WHEEL
mmsbm-1.0.5.dist-info/top_level.txt
mmsbm-1.0.5.dist-info/RECORD
