Metadata-Version: 2.4
Name: mmsbm
Version: 1.0.5
Summary: Compute Mixed Membership Stochastic Block Models.
Home-page: https://github.com/eudald-seeslab/mmsbm
Author: Eudald Correig
Author-email: eudald.correig@urv.cat
License: BSD-3-Clause License
Keywords: bayesian analysis,recommender systems,network analysis,python
Classifier: Development Status :: 4 - Beta
Classifier: Programming Language :: Python :: 3
Classifier: Intended Audience :: Science/Research
Classifier: Operating System :: OS Independent
Classifier: Topic :: Scientific/Engineering :: Artificial Intelligence
Requires-Python: >=3.7
License-File: LICENSE.txt
Requires-Dist: numpy
Requires-Dist: pandas
Requires-Dist: tqdm
Provides-Extra: dev
Requires-Dist: pytest>=3.7; extra == "dev"
Requires-Dist: pytest-cov; extra == "dev"
Requires-Dist: coveralls; extra == "dev"
Provides-Extra: numba
Requires-Dist: numba; extra == "numba"
Provides-Extra: cupy
Requires-Dist: cupy-cuda12x; extra == "cupy"
Dynamic: author
Dynamic: author-email
Dynamic: classifier
Dynamic: description
Dynamic: description-content-type
Dynamic: home-page
Dynamic: keywords
Dynamic: license
Dynamic: license-file
Dynamic: provides-extra
Dynamic: requires-dist
Dynamic: requires-python
Dynamic: summary
